<annotation>
	<folder>fssai_images</folder>
	<filename>38.jpg</filename>
	<path>/home/afzal/Desktop/fssai_images/38.jpg</path>
	<source>
		<database>Unknown</database>
	</source>
	<size>
		<width>660</width>
		<height>932</height>
		<depth>3</depth>
	</size>
	<segmented>0</segmented>
	<object>
		<name>fssai</name>
		<pose>Unspecified</pose>
		<truncated>0</truncated>
		<difficult>0</difficult>
		<bndbox>
			<xmin>521</xmin>
			<ymin>410</ymin>
			<xmax>588</xmax>
			<ymax>446</ymax>
		</bndbox>
	</object>
</annotation>
